qdbg/__init__.py
qdbg/__version__.py
qdbg/cli.py
qdbg-0.1.0.dist-info/LICENSE
qdbg-0.1.0.dist-info/WHEEL
qdbg-0.1.0.dist-info/METADATA
qdbg-0.1.0.dist-info/RECORD
