Metadata-Version: 2.1
Name: qdbg
Version: 0.1.0
Summary: a quick debugging cli tool
Home-page: https://github.com/hermgerm29/qdbg
License: MIT
Keywords: debugging,search
Author: Jimmy Herman
Author-email: jimmyherman29@gmail.com
Requires-Python: >=3.7,<4.0
Classifier: License :: OSI Approved :: MIT License
Classifier: Programming Language :: Python :: 3
Classifier: Programming Language :: Python :: 3.10
Classifier: Programming Language :: Python :: 3.7
Classifier: Programming Language :: Python :: 3.8
Classifier: Programming Language :: Python :: 3.9
Project-URL: Repository, https://github.com/hermgerm29/qdbg
